{"configName":"LCD-X 2021","accessKey":"","filterArray":[{"Filter01":{"type":"Peaking","freq":59,"gain":-0.6,"q":1.38}},{"Filter02":{"type":"Peaking","freq":104,"gain":-3.6,"q":0.23}},{"Filter03":{"type":"Lowshelf","freq":105,"gain":6,"q":0.7}},{"Filter04":{"type":"Peaking","freq":112,"gain":0.7,"q":1.47}},{"Filter05":{"type":"Peaking","freq":766,"gain":-2.6,"q":2.03}},{"Filter06":{"type":"Peaking","freq":1918,"gain":1.4,"q":4.73}},{"Filter07":{"type":"Peaking","freq":3757,"gain":6.6,"q":1.77}},{"Filter08":{"type":"Peaking","freq":5626,"gain":-1.4,"q":6}},{"Filter09":{"type":"Peaking","freq":8949,"gain":2,"q":2.36}},{"Filter10":{"type":"Highshelf","freq":10000,"gain":-4.8,"q":0.7}},{"Preamp":{"gain":-6.5}},{"Volume":{"type":"Volume","parameters":{}}}]}