{"configName":"Truthear Zero","filterArray":[{"Filter01":{"type":"Peaking","freq":64,"gain":0.5,"q":3.11}},{"Filter02":{"type":"Peaking","freq":65,"gain":-5,"q":0.88}},{"Filter03":{"type":"Peaking","freq":100,"gain":-0.8,"q":2.04}},{"Filter04":{"type":"Lowshelf","freq":105,"gain":2.4,"q":0.7}},{"Filter05":{"type":"Peaking","freq":180,"gain":1.4,"q":2.44}},{"Filter06":{"type":"Peaking","freq":317,"gain":-0.5,"q":2.05}},{"Filter07":{"type":"Peaking","freq":855,"gain":1.2,"q":1.55}},{"Filter08":{"type":"Peaking","freq":1534,"gain":-1.4,"q":1.16}},{"Filter09":{"type":"Peaking","freq":8301,"gain":2.3,"q":1.01}},{"Filter10":{"type":"Highshelf","freq":10000,"gain":-2,"q":0.7}},{"Preamp":{"gain":-1.8}}]}